{
  "special-events": [
    {
      "dates": ["20190331"],
      "city": "ciudad de mexico",
      "title": "Necesitas actualizar tu aplicación.",
      "text": "Esta versión no tendrá más soporte; para seguir recibiendo notificaciones debes descargar la nueva aplicación en el playstore. Ahora es Pipla - Hoy No Circula Mexico de Twelve Stars Software. Haz click en Leer Mas para llevar al nuevo enlace de descarga.",
      "url": "https://play.google.com/store/apps/details?id=com.twelvestars.pipla_mexico"
    }
  ],
  "country" : "mexico",
  "holidays": ["20180101", "20180205", "20180319", "20180501","20181119", "20181225",
    "20190101", "20190204", "20190318", "20190501","20190916", "20191118", "20191225"],
  "cities": [
    {
      "name": "ciudad de mexico",
      "unrestricted-days": [],
      "restrictions": [
        {
          "days": ["mon", "tue", "wed", "thu", "fri"],
          "hours":[
            {
              "from": "5",
              "to": "22"
            }
          ],
          "validator": {
            "type": "static",
            "restrictions": [
              {
                "day": "mon",
                "plates": [ "5", "6"]
              },
              {
                "day": "tue",
                "plates": [ "7", "8"]
              },
              {
                "day": "wed",
                "plates": [ "3", "4"]
              },
              {
                "day": "thu",
                "plates": [ "1", "2"]
              },
              {
                "day": "fri",
                "plates": [ "9", "0"]
              }
            ]
          }
        },
        {
          "days": ["sat"],
          "hours":[
            {
              "from": "5",
              "to": "22"
            }
          ],
          "validator": {
            "type": "pair-impair",
            "evaluator": "WEEK_OF_YEAR",
            "pair-if-pair": "false"
          }
        },
        {
          "days": [ "20180922", "20190922", "20200922", "20210922", "20220922"],
          "hours":[
            {
              "from": "5",
              "to": "22"
            }
          ],
          "validator": {
            "type": "plates-by-day",
            "monday-start": "0",
            "plates-by-day": "10"
          }
        }
      ]
    }
  ]
}